textprobability/__init__.py
textprobability/classify.py
textprobability/core/__init__.py
textprobability/core/common.py
textprobability/core/defaults.py
textprobability/core/lexicon.py
textprobability/core/mpf.py
textprobability/core/splitters.py
textprobability/core/types.py
textprobability/data/__init__.py
textprobability/data/de.json
textprobability/data/en.json
textprobability/data/es.json
textprobability/data/fr.json
textprobability/data/get_data.py
textprobability/data/it.json
textprobability/data/langdata.py
textprobability/data/pt.json
textprobability/data/summarize.py
textprobability/data/tr.json
textprobability/data/web_walk.py
textprobability/examples/__init__.py
textprobability/examples/classification.py
textprobability/examples/defaults.py
textprobability-0.0.3.dist-info/LICENSE
textprobability-0.0.3.dist-info/METADATA
textprobability-0.0.3.dist-info/WHEEL
textprobability-0.0.3.dist-info/top_level.txt
textprobability-0.0.3.dist-info/RECORD
