Metadata-Version: 2.1
Name: textprobability
Version: 0.0.3
Summary: Coarse estimation of the probability of observing a string in a given body of text.
Home-page: https://github.com/ancient-world-citation-analysis/textprobability
Author: Peter Donovan
Author-email: peterdonovan@berkeley.edu
License: UNKNOWN
Project-URL: Bug Tracker, https://github.com/ancient-world-citation-analysis/textprobability/issues
Platform: UNKNOWN
Classifier: Programming Language :: Python :: 3
Classifier: License :: OSI Approved :: MIT License
Classifier: Operating System :: OS Independent
Requires-Python: >=3.5
License-File: LICENSE
Requires-Dist: numpy
